[
    {
        "projectName": "KP Yatzy",
        "thumbnail": "https://screenshot-proxy.netlify.app/f_avif,w_336/https://d33wubrfki0l68.cloudfront.net/644f9e15847cab051ded1893/screenshot_2023-05-01-11-10-29-0000.png",
        "links": {
            "ui": "https://kpyatzy.netlify.app/",
            "code": "https://github.com/KrisPersson/yatzy-game"
        },
        "tech": [
            "html", "css", "js"
        ]
    },
    {
        "projectName": "KP Four-In-a-Row",
        "thumbnail": "https://screenshot-proxy.netlify.app/f_avif,w_204/https://d33wubrfki0l68.cloudfront.net/644f9c4fcbc6c4051f1d0c51/screenshot_2023-05-01-11-02-56-0000.png",
        "links": {
            "ui": "https://kpfourinarow.netlify.app",
            "code": "https://github.com/KrisPersson/four-in-a-row-game"
        },
        "tech": [
            "html", "css", "js"
        ]
    },
    {
        "projectName": "KP Bonzai",
        "thumbnail": "https://screenshot-proxy.netlify.app/f_avif,w_204/https://d33wubrfki0l68.cloudfront.net/63402388a2154900087a4d5a/screenshot_2022-10-07-13-03-14-0000.png",
        "links": {
            "ui": "https://kpbonzai.netlify.app",
            "code": "https://github.com/KrisPersson/four-in-a-row-game"
        },
        "tech": [
            "html", "css"
        ]
    }
]